{
"UpdateVersion" : "7.5",
"UpdateMessage" : "Sorry we are closed 🙏",
"UpdateUrl" : "",

"InfoVersion" : "true",
"InfoMessage" : "New video",
"InfoButtonOk" : "watch",
"InfoUrl" : "https://youtu.be/eaATUfHoOtw",

"Antena" : "assetindexer.8~2FDinOIgg9lz07Rd~2BaRxwEkU4yw~3D",
"Map" : "optionalmap_1.8H~2F6c9GukhwMi8hgcu8CjY6un4s~3D",
"LayoutMessage" : "New Update Patch BOOYAH Day
FFData Version 1.54.2
Server Antena Update :
Antena Head √
Antena Hand √
Antena Plus x
Map Purgatory HD √

'DONT USE MAIN ACCOUNT RISK BANNED'"
}
